setup.py
huoyanlib/__init__.py
huoyanlib/c.py
huoyanlib/log_in.py
huoyanlib/print.py
huoyanlib/print_logo.py
huoyanlib/python_plot.py
huoyanlib/spark_word.py
huoyanlib.egg-info/PKG-INFO
huoyanlib.egg-info/SOURCES.txt
huoyanlib.egg-info/dependency_links.txt
huoyanlib.egg-info/top_level.txt
huoyanlib/request/__init__.py
huoyanlib/request/get_news.py
huoyanlib/request/internal_module.py
huoyanlib/request/xes.py
huoyanlib_old/__init__.py
huoyanlib_old/calculator.py
huoyanlib_old/check.py
huoyanlib_old/counter.py
huoyanlib_old/help.py
huoyanlib_old/log_in.py
huoyanlib_old/practise_typing.py
huoyanlib_old/print.py
huoyanlib_old/print_logo.py
huoyanlib_old/spark_word.py
huoyanlib_old/translater.py
huoyanlib_old/orangeslib/__init__.py
huoyanlib_old/orangeslib/cz_clear.py
huoyanlib_old/orangeslib/cz_pinyin.py
huoyanlib_old/orangeslib/cz_print.py
huoyanlib_old/orangeslib/cz_qrcode.py