Metadata-Version: 2.1
Name: huoyanlib
Version: 2.2.0
Summary: 学而思火焰工作室专属库
Home-page: https://github.com/
Author: RuiQin Li
Author-email: 2647154420@qq.com
License: UNKNOWN
Platform: UNKNOWN
Classifier: Programming Language :: Python :: 3
Classifier: License :: OSI Approved :: MIT License
Classifier: Operating System :: OS Independent
